render_html/__init__.py
render_html/_renderer.py
render_html/exceptions.py
render_html-1.0.1.dist-info/LICENSE
render_html-1.0.1.dist-info/METADATA
render_html-1.0.1.dist-info/WHEEL
render_html-1.0.1.dist-info/top_level.txt
render_html-1.0.1.dist-info/RECORD
