Metadata-Version: 2.1
Name: render_html
Version: 1.0.1
Summary: Python library that provides a simple way to render HTML content in a web browser.
Author-email: Bartlomiej Mika <bmika1@icloud.com>
Project-URL: Homepage, https://github.com/bmika1/render-html
Project-URL: Bug Tracker, https://github.com/bmika1/render-html/issues
Classifier: Programming Language :: Python :: 3
Classifier: License :: OSI Approved :: MIT License
Classifier: Operating System :: OS Independent
Requires-Python: >=3.10
License-File: LICENSE
